VHDLTest/Configuration.py
VHDLTest/VHDLTest.py
VHDLTest/__init__.py
VHDLTest/__main__.py
VHDLTest/logger/Log.py
VHDLTest/logger/LogConsole.py
VHDLTest/logger/LogFile.py
VHDLTest/logger/LogItem.py
VHDLTest/logger/LogWriter.py
VHDLTest/logger/__init__.py
VHDLTest/runner/RunResults.py
VHDLTest/runner/__init__.py
VHDLTest/simulator/ActiveHDL.py
VHDLTest/simulator/GHDL.py
VHDLTest/simulator/SimulatorBase.py
VHDLTest/simulator/SimulatorFactory.py
VHDLTest/simulator/__init__.py
VHDLTest-0.2.0.dist-info/LICENSE
VHDLTest-0.2.0.dist-info/METADATA
VHDLTest-0.2.0.dist-info/WHEEL
VHDLTest-0.2.0.dist-info/entry_points.txt
VHDLTest-0.2.0.dist-info/top_level.txt
VHDLTest-0.2.0.dist-info/RECORD
