Metadata-Version: 2.1
Name: VHDLTest
Version: 0.2.0
Summary: VHDL Testbench Runner
Home-page: https://github.com/Malcolmnixon/VhdlTest
Author: Malcolm Nixon
License: UNKNOWN
Platform: UNKNOWN
Classifier: Programming Language :: Python :: 3
Classifier: License :: OSI Approved :: MIT License
Classifier: Operating System :: OS Independent
Requires-Python: >=3.7
Requires-Dist: PyYAML
Requires-Dist: colorama
Requires-Dist: junit-xml
